cli/.env
cli/__init__.py
cli/agents.py
cli/connectors.py
cli/functions.py
cli/setup.py
cli/wowbits.py
cli/data/providers.json
db/__init__.py
db/schema.py
db/alembic/README.md
db/alembic/alembic.ini
db/alembic/env.py
db/alembic/script.py.mako
db/alembic/versions/2026_01_04_1404-a17f8d0d25fe_adding_table_for_connectors.py
pylibs/__init__.py
pylibs/connector.py
pylibs/database_manager.py
pylibs/env_loader.py
wowbits_cli-0.1.0a3.dist-info/METADATA
wowbits_cli-0.1.0a3.dist-info/WHEEL
wowbits_cli-0.1.0a3.dist-info/entry_points.txt
wowbits_cli-0.1.0a3.dist-info/RECORD
