Metadata-Version: 2.4
Name: wowbits-cli
Version: 0.1.0a3
Summary: WowBits AI Platform CLI - Manage connectors and integrations for AI workflows
Project-URL: Homepage, https://github.com/wowbits/wowbits-cli
Project-URL: Documentation, https://github.com/wowbits/wowbits-cli#readme
Project-URL: Repository, https://github.com/wowbits/wowbits-cli
Project-URL: Issues, https://github.com/wowbits/wowbits-cli/issues
Author-email: WowBits AI <support@wowbits.ai>
License: MIT
Keywords: ai,api-management,cli,connectors,integrations,wowbits
Classifier: Development Status :: 4 - Beta
Classifier: Environment :: Console
Classifier: Intended Audience :: Developers
Classifier: License :: OSI Approved :: MIT License
Classifier: Operating System :: OS Independent
Classifier: Programming Language :: Python :: 3
Classifier: Programming Language :: Python :: 3.9
Classifier: Programming Language :: Python :: 3.10
Classifier: Programming Language :: Python :: 3.11
Classifier: Programming Language :: Python :: 3.12
Classifier: Topic :: Software Development :: Libraries :: Python Modules
Classifier: Topic :: Utilities
Requires-Python: >=3.9
Requires-Dist: psycopg2-binary>=2.9.0
Requires-Dist: python-dotenv>=1.0.0
Requires-Dist: sqlalchemy>=2.0.0
Provides-Extra: dev
Requires-Dist: black>=23.0.0; extra == 'dev'
Requires-Dist: pytest-cov>=4.0.0; extra == 'dev'
Requires-Dist: pytest>=7.0.0; extra == 'dev'
Requires-Dist: ruff>=0.1.0; extra == 'dev'
